.codeclimate.yml
.coveragerc
.editorconfig
.gitignore
.travis.yml
LICENSE
MANIFEST.in
Makefile
README.rst
default.nix
requirements-dev.txt
setup.cfg
setup.py
tox.ini
docs/Makefile
docs/campaign.rst
docs/conf.py
docs/hpcbench.rst
docs/index.rst
docs/make.bat
docs/modules.rst
docs/standard_benchmark.rst
hpcbench/__init__.py
hpcbench/api.py
hpcbench/campaign.py
hpcbench/report.py
hpcbench/template.py
hpcbench.egg-info/PKG-INFO
hpcbench.egg-info/SOURCES.txt
hpcbench.egg-info/dependency_links.txt
hpcbench.egg-info/entry_points.txt
hpcbench.egg-info/requires.txt
hpcbench.egg-info/top_level.txt
hpcbench/benchmark/__init__.py
hpcbench/benchmark/babelstream.py
hpcbench/benchmark/basic.bash
hpcbench/benchmark/basic.py
hpcbench/benchmark/custream.py
hpcbench/benchmark/hpl.py
hpcbench/benchmark/imb.py
hpcbench/benchmark/ionvme.py
hpcbench/benchmark/ior.py
hpcbench/benchmark/iperf.py
hpcbench/benchmark/mdtest.py
hpcbench/benchmark/minigemm.py
hpcbench/benchmark/nvidia.py
hpcbench/benchmark/osu.py
hpcbench/benchmark/shoc.py
hpcbench/benchmark/standard.py
hpcbench/benchmark/stream.py
hpcbench/benchmark/sysbench.py
hpcbench/cli/__init__.py
hpcbench/cli/bencsv.py
hpcbench/cli/bendoc.py
hpcbench/cli/benelastic.py
hpcbench/cli/benmerge.py
hpcbench/cli/bennett.py
hpcbench/cli/bensh.py
hpcbench/cli/bentpl.py
hpcbench/cli/benumb.py
hpcbench/cli/benwait.py
hpcbench/driver/__init__.py
hpcbench/driver/base.py
hpcbench/driver/benchmark.py
hpcbench/driver/campaign.py
hpcbench/driver/executor.py
hpcbench/driver/slurm.py
hpcbench/export/__init__.py
hpcbench/export/csvexport.py
hpcbench/export/es.py
hpcbench/net/__init__.py
hpcbench/templates/HPL.dat.jinja
hpcbench/templates/executor.sh.jinja
hpcbench/templates/hpcbench.yaml.jinja
hpcbench/templates/report.tex.jinja
hpcbench/templates/sbatch.jinja
hpcbench/templates/ssh-installer.sh.jinja
hpcbench/templates/plugins/benchmark/cookiecutter.json
hpcbench/templates/plugins/benchmark/hooks/pre_gen_project.py
hpcbench/templates/plugins/benchmark/{{cookiecutter.benchmark}}/setup.py
hpcbench/templates/plugins/benchmark/{{cookiecutter.benchmark}}/hpcbench_{{cookiecutter.benchmark}}/benchmark.py
hpcbench/toolbox/__init__.py
